deep_sort_realtime/__init__.py
deep_sort_realtime/deepsort_tracker.py
deep_sort_realtime/deep_sort/__init__.py
deep_sort_realtime/deep_sort/detection.py
deep_sort_realtime/deep_sort/iou_matching.py
deep_sort_realtime/deep_sort/kalman_filter.py
deep_sort_realtime/deep_sort/linear_assignment.py
deep_sort_realtime/deep_sort/nn_matching.py
deep_sort_realtime/deep_sort/track.py
deep_sort_realtime/deep_sort/tracker.py
deep_sort_realtime/embedder/__init__.py
deep_sort_realtime/embedder/embedder_clip.py
deep_sort_realtime/embedder/embedder_pytorch.py
deep_sort_realtime/embedder/embedder_tf.py
deep_sort_realtime/embedder/mobilenetv2_bottle.py
deep_sort_realtime/embedder/weights/download_tf_wts.sh
deep_sort_realtime/embedder/weights/mobilenetv2_bottleneck_wts.pt
deep_sort_realtime/utils/__init__.py
deep_sort_realtime/utils/nms.py
deep_sort_realtime-1.3.1.dist-info/LICENSE
deep_sort_realtime-1.3.1.dist-info/METADATA
deep_sort_realtime-1.3.1.dist-info/WHEEL
deep_sort_realtime-1.3.1.dist-info/top_level.txt
deep_sort_realtime-1.3.1.dist-info/RECORD
