Metadata-Version: 2.1
Name: deep-sort-realtime
Version: 1.3.1
Summary: A more realtime adaptation of Deep SORT
Home-page: https://github.com/levan92/deep_sort_realtime
Author: levan92
Author-email: lingevan0208@gmail.com
Classifier: Programming Language :: Python :: 3
Classifier: License :: OSI Approved :: MIT License
Classifier: Operating System :: OS Independent
License-File: LICENSE
Requires-Dist: numpy
Requires-Dist: scipy
Requires-Dist: opencv-python
